mvn/__init__.py
mvn/main.py
mvn_utils-1.0.6.dist-info/METADATA
mvn_utils-1.0.6.dist-info/WHEEL
mvn_utils-1.0.6.dist-info/entry_points.txt
mvn_utils-1.0.6.dist-info/top_level.txt
mvn_utils-1.0.6.dist-info/RECORD
