Metadata-Version: 2.1
Name: mvn-utils
Version: 1.0.6
Summary: code sdk
Home-page: https://xxx.com
Author: xuwuqiang
Author-email: xwqiang2008@outlook.com
License: MIT Licence
Keywords: mvn utils,java dependencies
Platform: any
Requires-Dist: setuptools (==65.6.3)
